pymtom/__init__.py
pymtom/create.py
pymtom/parse.py
pymtom-0.3.1.dist-info/METADATA
pymtom-0.3.1.dist-info/WHEEL
pymtom-0.3.1.dist-info/RECORD
