Metadata-Version: 2.1
Name: pymtom
Version: 0.3.1
Summary: 
Author: Mirek Zvolský
Author-email: zvolsky@seznam.cz
Requires-Python: >=3.7,<4.0
Classifier: Programming Language :: Python :: 3
Classifier: Programming Language :: Python :: 3.7
Classifier: Programming Language :: Python :: 3.8
Classifier: Programming Language :: Python :: 3.9
Classifier: Programming Language :: Python :: 3.10
Classifier: Programming Language :: Python :: 3.11
Requires-Dist: zeep (>=4.2.1,<5.0.0)
